avnet/iotconnect/sdk/sdklib/__init__.py
avnet/iotconnect/sdk/sdklib/config.py
avnet/iotconnect/sdk/sdklib/dra.py
avnet/iotconnect/sdk/sdklib/error.py
avnet/iotconnect/sdk/sdklib/mqtt.py
avnet/iotconnect/sdk/sdklib/util.py
avnet/iotconnect/sdk/sdklib/version.py
avnet/iotconnect/sdk/sdklib/protocol/__init__.py
avnet/iotconnect/sdk/sdklib/protocol/c2d.py
avnet/iotconnect/sdk/sdklib/protocol/d2c.py
avnet/iotconnect/sdk/sdklib/protocol/discovery.py
avnet/iotconnect/sdk/sdklib/protocol/files.py
avnet/iotconnect/sdk/sdklib/protocol/identity.py
iotconnect_lib-1.0.1.dist-info/licenses/LICENSE.md
iotconnect_lib-1.0.1.dist-info/METADATA
iotconnect_lib-1.0.1.dist-info/WHEEL
iotconnect_lib-1.0.1.dist-info/top_level.txt
iotconnect_lib-1.0.1.dist-info/RECORD
