Metadata-Version: 2.4
Name: iotconnect-lib
Version: 1.0.1
Summary: Avnet IoTConnect SDK Library
Author-email: Nik Markovic <nikola.markovic@avnet.com>
Project-URL: Homepage, https://github.com/avnet-iotconnect/iotc-python-lib
Keywords: IoTconnect,AWS,IoTCore,Azure,IoTHub,Greengrass
Classifier: Development Status :: 3 - Alpha
Classifier: Intended Audience :: Developers
Classifier: License :: OSI Approved :: MIT License
Classifier: Natural Language :: English
Classifier: Operating System :: MacOS :: MacOS X
Classifier: Operating System :: Microsoft :: Windows
Classifier: Operating System :: POSIX
Classifier: Programming Language :: Python
Classifier: Programming Language :: Python :: 3
Classifier: Programming Language :: Python :: 3.9
Classifier: Programming Language :: Python :: 3.10
Classifier: Programming Language :: Python :: 3.11
Classifier: Programming Language :: Python :: 3.12
Classifier: Topic :: Communications
Classifier: Topic :: Internet
Requires-Python: >=3.9
License-File: LICENSE.md
Provides-Extra: test
Requires-Dist: pytest; extra == "test"
Requires-Dist: pytest-cov; extra == "test"
Dynamic: license-file
